alphasign/__init__.py
alphasign/animations.py
alphasign/easy.py
alphasign/image.py
alphasign/modes.py
alphasign/packet.py
alphasign/sign.py
alphasign/singleton.py
alphasign/text.py
alphasign/transitions.py
alphasign/types.py
alphasign/command/__init__.py
alphasign/command/write_small_dots.py
alphasign/command/write_special_functions.py
alphasign/command/write_text.py
alphasign/files/__init__.py
alphasign/files/text.py
alphasign/type/__init__.py
alphasign/type/_common.py
alphasign/type/all.py
alphasign/type/alpha_2x0c.py
pyalphasign-0.1.0.dist-info/LICENSE
pyalphasign-0.1.0.dist-info/METADATA
pyalphasign-0.1.0.dist-info/WHEEL
pyalphasign-0.1.0.dist-info/top_level.txt
pyalphasign-0.1.0.dist-info/RECORD
