Metadata-Version: 2.1
Name: pyalphasign
Version: 0.1.0
Summary: An implementation of Alpha/BetaBrite/Adaptive LED signs protocol
Author-email: prototux <jason@prototux.net>
License: Apache License
Project-URL: Homepage, https://github.com/prototux/python-alphasign
Project-URL: Bug Tracker, https://github.com/prototux/python-alphasign/issues
Keywords: alphasign,betabrite,LED Sign,alpha protocol,adaptive displays
Classifier: Development Status :: 4 - Beta
Classifier: Programming Language :: Python :: 3
Classifier: License :: OSI Approved :: Apache Software License
Classifier: Operating System :: OS Independent
Requires-Python: >=3.7
License-File: LICENSE
Requires-Dist: Pillow (>9.4.0)
Requires-Dist: pyserial (>3.4)
